deepsplines/__init__.py
deepsplines/dataloader.py
deepsplines/datasets.py
deepsplines/ds_utils.py
deepsplines/main.py
deepsplines/manager.py
deepsplines/project.py
deepsplines/struct_default_values.py
deepsplines/ds_modules/__init__.py
deepsplines/ds_modules/basemodel.py
deepsplines/ds_modules/deepBspline.py
deepsplines/ds_modules/deepBspline_base.py
deepsplines/ds_modules/deepBspline_explicit_linear.py
deepsplines/ds_modules/deepReLUspline.py
deepsplines/ds_modules/deepspline_base.py
deepsplines/ds_modules/dsnn.py
deepsplines/networks/__init__.py
deepsplines/networks/convnet_mnist.py
deepsplines/networks/nin_cifar.py
deepsplines/networks/resnet_cifar.py
deepsplines/networks/twoDnet.py
deepsplines-1.0.0.data/scripts/approximate_parabola.py
deepsplines-1.0.0.data/scripts/deepsplines_tutorial.py
deepsplines-1.0.0.data/scripts/generate_save_twoD_dataset.py
deepsplines-1.0.0.data/scripts/main.py
deepsplines-1.0.0.data/scripts/plot_activations.py
deepsplines-1.0.0.data/scripts/plot_deepspline_basis.py
deepsplines-1.0.0.data/scripts/plot_sparsity_error_rate_lipschitz_bound_vs_lmbda.py
deepsplines-1.0.0.data/scripts/print_ckpt_params_acc.py
deepsplines-1.0.0.data/scripts/run_nin_cifar.py
deepsplines-1.0.0.data/scripts/run_resnet32_cifar.py
deepsplines-1.0.0.data/scripts/run_twoDnet.py
deepsplines-1.0.0.data/scripts/sparsify_with_optimal_knot_threshold.py
deepsplines-1.0.0.dist-info/LICENSE
deepsplines-1.0.0.dist-info/METADATA
deepsplines-1.0.0.dist-info/WHEEL
deepsplines-1.0.0.dist-info/top_level.txt
deepsplines-1.0.0.dist-info/RECORD
