Metadata-Version: 2.1
Name: deepsplines
Version: 1.0.0
Summary: A framework to train the activation functions of a neural network
Home-page: https://github.com/joaquimcampos/DeepSplines
Author: Joaquim Campos
Author-email: joaquimcampos15@hotmail.com
License: MIT
Project-URL: Bug Tracker, https://github.com/joaquimcampos/DeepSplines/issues
Keywords: activation functions,B-splines,deep learning,regularization,sparsity
Platform: UNKNOWN
Classifier: Development Status :: 3 - Alpha
Classifier: Intended Audience :: Developers
Classifier: Topic :: Scientific/Engineering :: Artificial Intelligence
Classifier: License :: OSI Approved :: MIT License
Classifier: Natural Language :: English
Classifier: Programming Language :: Python :: 3
Requires-Python: >=3.7
License-File: LICENSE
Requires-Dist: numpy (>=1.10)
Requires-Dist: torch (>=1.5.1)
Requires-Dist: torchvision (>=0.2.2)
Requires-Dist: matplotlib (>=3.3.1)
Provides-Extra: dev
Requires-Dist: autopep8 ; extra == 'dev'
Requires-Dist: flake8 ; extra == 'dev'
Requires-Dist: yapf ; extra == 'dev'
